ez_data_pipeline/__init__.py
ez_data_pipeline/Foundation/__init__.py
ez_data_pipeline/Foundation/utils.py
ez_data_pipeline/Foundation/default_pipeline/Iimporter.py
ez_data_pipeline/Foundation/default_pipeline/Imodel.py
ez_data_pipeline/Foundation/default_pipeline/Ipipeline.py
ez_data_pipeline/Foundation/default_pipeline/Iproccess.py
ez_data_pipeline/Foundation/default_pipeline/IproccessMethod.py
ez_data_pipeline/Foundation/default_pipeline/Isave.py
ez_data_pipeline/Foundation/default_pipeline/__init__.py
ez_data_pipeline/Pipeline/__init__.py
ez_data_pipeline-0.6.dist-info/METADATA
ez_data_pipeline-0.6.dist-info/WHEEL
ez_data_pipeline-0.6.dist-info/top_level.txt
ez_data_pipeline-0.6.dist-info/RECORD
