Metadata-Version: 2.1
Name: ez-data-pipeline
Version: 0.6
Summary: Object Oriented Library to create data pipelines
Home-page: https://github.com/VexedIOS/open_data_pipeline
Author: Juan(VexedIOS)
Author-email: juanteams@outlook.com
License: MIT
Classifier: License :: OSI Approved :: MIT License
Classifier: Programming Language :: Python :: 3.10
Classifier: Operating System :: OS Independent
Requires-Python: >=3.8
Requires-Dist: pandas (>=2.0.1)
Provides-Extra: dev
Requires-Dist: pytest (>=7.0) ; extra == 'dev'
Requires-Dist: twine (>=4.0.2) ; extra == 'dev'
Requires-Dist: yfinance (>=0.2.18) ; extra == 'dev'
